Metadata-Version: 1.0
Name: sphinx-runner
Version: 0.1.0
Summary: A sphinx-runner for setuptools
Home-page: UNKNOWN
Author: Jakob Jul Elben
Author-email: elbenjakobjul@gmail.com
License: UNKNOWN
Platform: UNKNOWN
